{
  "type": "ui_update",
  "content": "🍄 Yahoo! Let's-a go! I've transformed everything into a super Mario wonderland! 🌟 The colors are inspired by Mario's iconic look - red, blue, and mushroom kingdom colors! 👑",
  "ui_changes": {
    "primary_color": "#e52521",
    "secondary_color": "#2b9bf4",
    "background_color": "#89CFF0",
    "text_color": "#333333",
    "page_bg": "#89CFF0",
    "bubble_size": "1.2rem",
    "bubble_padding": "15px",
    "bubble_radius": "20px",
    "bubble_shadow": "0 4px 8px rgba(0,0,0,0.2)",
    "bubble_max_width": "75%",
    "font_family": "'Press Start 2P', system-ui, monospace",
    "font_size": "14px",
    "line_height": "1.6",
    "spacing": "20px",
    "chat_container_max_width": "680px",
    "animation_speed": "0.3s",
    "transition_effect": "bounce",
    "border_width": "3px",
    "border_style": "solid",
    "border_color": "#fbd000",
    "global_border_radius": "20px",
    "input_background": "#ffffff",
    "chat_background": "#def3ff",
    "header_background": "#e52521",
    "header_text_color": "#ffffff",
    "user_message_background": "#2b9bf4",
    "user_message_text_color": "#ffffff",
    "assistant_message_background": "#fbd000",
    "assistant_message_text_color": "#333333",
    "message_margin_bottom": "24px",
    "user_message_border_color": "#1a8ae3",
    "assistant_message_border_color": "#e5be00",
    "button_icon_color": "#ffffff",
    "send_button_bg": "#e52521",
    "send_button_color": "#ffffff",
    "attachment_button_bg": "#2b9bf4",
    "attachment_button_color": "#ffffff",
    "info_button_color": "#ffffff"
  },
  "currentState": {
    "primary_color": "#e52521",
    "secondary_color": "#2b9bf4",
    "background_color": "#89CFF0",
    "text_color": "#333333",
    "page_bg": "#89CFF0",
    "bubble_size": "1.2rem",
    "bubble_padding": "15px",
    "bubble_radius": "20px",
    "bubble_shadow": "0 4px 8px rgba(0,0,0,0.2)",
    "bubble_max_width": "75%",
    "font_family": "'Press Start 2P', system-ui, monospace",
    "font_size": "14px",
    "line_height": "1.6",
    "spacing": "20px",
    "chat_container_max_width": "680px",
    "animation_speed": "0.3s",
    "transition_effect": "bounce",
    "border_width": "3px",
    "border_style": "solid",
    "border_color": "#fbd000",
    "global_border_radius": "20px",
    "input_background": "#ffffff",
    "chat_background": "#def3ff",
    "header_background": "#e52521",
    "header_text_color": "#ffffff",
    "user_message_background": "#2b9bf4",
    "user_message_text_color": "#ffffff",
    "assistant_message_background": "#fbd000",
    "assistant_message_text_color": "#333333",
    "message_margin_bottom": "24px",
    "user_message_border_color": "#1a8ae3",
    "assistant_message_border_color": "#e5be00",
    "button_icon_color": "#ffffff",
    "send_button_bg": "#e52521",
    "send_button_color": "#ffffff",
    "attachment_button_bg": "#2b9bf4",
    "attachment_button_color": "#ffffff",
    "info_button_color": "#ffffff"
  }
}